NavigatorPython.py
NavigatorTest.pyd
advantech_daq_python-0.0.5.dist-info/LICENSE
advantech_daq_python-0.0.5.dist-info/METADATA
advantech_daq_python-0.0.5.dist-info/WHEEL
advantech_daq_python-0.0.5.dist-info/top_level.txt
advantech_daq_python-0.0.5.dist-info/RECORD
